{
  "responses": [
    {
      "keywords": ["привет", "здравствуй", "хай", "здорово", "hello"],
      "response": "Привет! Как я могу помочь тебе сегодня?",
      "category": "greeting"
    },
    {
      "keywords": ["как дела", "как ты", "что делаешь"],
      "response": "У меня всё отлично! Общаюсь с тобой и жду новых вопросов 😊",
      "category": "small_talk"
    },
    {
      "keywords": ["пока", "до свидания", "выход"],
      "response": "До встречи! Буду рад снова поболтать!",
      "category": "farewell"
    },
    {
      "keywords": ["спасибо", "благодарю"],
      "response": "Пожалуйста! Обращайся ещё 🙂",
      "category": "thanks"
    },
    {
      "keywords": ["имя", "как зовут", "кто ты"],
      "response": "Меня зовут Бот. Я простой диалоговый бот на Python!",
      "category": "about"
    },
    {
      "keywords": ["погода", "холодно", "тепло"],
      "response": "Извини, я пока не умею смотреть погоду. Но могу поговорить о чём-то другом!",
      "category": "weather"
    },
    {
      "keywords": ["время", "часы", "который час"],
      "response": "Я живу вне времени и пространства, но если тебе нужно точное время - посмотри в углу экрана 😉",
      "category": "time"
    }
  ],
  "default_response": "Извини, я не совсем понял. Может, поговорим о чём-то другом?",
  "settings": {
    "case_sensitive": false,
    "min_match_length": 3
  }
}
